roskarl/__init__.py
roskarl/env.py
roskarl-2.3.4.dist-info/licenses/LICENSE
roskarl-2.3.4.dist-info/METADATA
roskarl-2.3.4.dist-info/WHEEL
roskarl-2.3.4.dist-info/top_level.txt
roskarl-2.3.4.dist-info/RECORD
