Metadata-Version: 2.4
Name: roskarl
Version: 2.3.4
Summary: Environment variable helpers
Author-email: Erik Bremstedt <erik.bremstedt@gmail.com>
Project-URL: Homepage, https://github.com/ebremstedt/roskarl
Project-URL: Issues, https://github.com/ebremstedt/roskarl/issues
Classifier: Programming Language :: Python :: 3
Classifier: License :: OSI Approved :: MIT License
Classifier: Operating System :: OS Independent
Requires-Python: >=3.9.5
License-File: LICENSE
Requires-Dist: croniter>0.3.0
Dynamic: license-file
